{"type":"Topology","objects":{"MNP_m50_a0_country_g":{"type":"GeometryCollection","geometries":[{"type":"MultiPolygon","properties":{"ne_adm0_a3":"MNP","ne_sov_a3":"US1","ne_gu_a3":"MNP","iso_3166_1_a3":"MNP","iso_3166_1_a2":"MP","ne_type":"Dependency","formal_name":"Commonwealth of the Northern Mariana Islands","name":"N. Mariana Is.","continent":"Oceania","subregion":"Micronesia","region_un":"Oceania","region_wb":"East Asia & Pacific"},"arcs":[[[0]],[[1]],[[2]],[[3]],[[4]],[[5]]]}]}},"arcs":[[[1649,100],[-724,-100],[-523,21],[-325,33],[-77,57],[1175,55],[483,-19],[-9,-47]],[[7465,1830],[-604,-109],[-430,169],[-72,68],[558,63],[330,-2],[218,-189]],[[8777,2176],[-40,-55],[-746,13],[-204,25],[423,192],[1070,88],[520,19],[-487,-91],[-91,-103],[-445,-88]],[[8194,4744],[-320,-15],[-467,8],[-326,33],[-73,57],[943,3],[352,-42],[-109,-44]],[[9152,8449],[-709,-47],[880,210],[266,37],[410,-77],[-847,-123]],[[8140,9905],[-443,-80],[-375,59],[-102,115],[653,-11],[241,-24],[26,-59]]],"transform":{"scale":[0.00006833691181617706,0.00046959285772327317],"translate":[145.15214843750007,14.111328125000014]}}