{"type":"Topology","objects":{"KOR_m110_a0_country_g":{"type":"GeometryCollection","geometries":[{"type":"Polygon","properties":{"ne_adm0_a3":"KOR","ne_sov_a3":"KOR","ne_gu_a3":"KOR","iso_3166_1_a3":"KOR","iso_3166_1_a2":"KR","ne_type":"Sovereign country","formal_name":"Republic of Korea","name":"Korea","continent":"Asia","subregion":"Eastern Asia","region_un":"Asia","region_wb":"East Asia & Pacific"},"arcs":[[0]]}]}},"arcs":[[[6661,9999],[2576,-2794],[739,-1535],[23,-2728],[-1125,-1302],[-2702,-455],[-2385,-982],[-2688,-203],[-334,1290],[553,1776],[-1318,2465],[2216,399],[-2045,2026],[187,215],[1332,-84],[1162,1069],[2109,114],[1271,156],[429,573]]],"transform":{"scale":[0.0003351241699704181,0.0004222619324123782],"translate":[126.11739790253229,34.39004588473648]}}